cli.py
main.py
server.py
audit/__init__.py
audit/scorer.py
docufix_ai-0.1.0.dist-info/licenses/LICENSE
generator/__init__.py
generator/llms_txt.py
generator/mcp_server.py
parser/__init__.py
parser/web.py
docufix_ai-0.1.0.dist-info/METADATA
docufix_ai-0.1.0.dist-info/WHEEL
docufix_ai-0.1.0.dist-info/entry_points.txt
docufix_ai-0.1.0.dist-info/top_level.txt
docufix_ai-0.1.0.dist-info/RECORD
