Metadata-Version: 2.4
Name: docufix-ai
Version: 0.1.0
Summary: AI Compatibility Audit & Enhancement Suite
Author-email: Antigravity <ai@example.com>
License: MIT License
Project-URL: Homepage, https://github.com/yourusername/DocuFix-CLI
Project-URL: Repository, https://github.com/yourusername/DocuFix-CLI
Project-URL: Issues, https://github.com/yourusername/DocuFix-CLI/issues
Keywords: AI,RAG,Documentation,GEO,MCP,Audit
Classifier: Development Status :: 4 - Beta
Classifier: Intended Audience :: Developers
Classifier: Topic :: Software Development :: Documentation
Classifier: License :: OSI Approved :: MIT License
Classifier: Programming Language :: Python :: 3.10
Classifier: Programming Language :: Python :: 3.11
Classifier: Programming Language :: Python :: 3.12
Requires-Python: >=3.10
License-File: LICENSE
Requires-Dist: typer[all]
Requires-Dist: rich
Requires-Dist: beautifulsoup4
Requires-Dist: playwright
Requires-Dist: tiktoken
Requires-Dist: mcp
Dynamic: license-file
